yggdrasil_shared/__init__.py
yggdrasil_shared/adapters.py
yggdrasil_shared/dependencies.py
yggdrasil_shared/encoders.py
yggdrasil_shared/events.py
yggdrasil_shared/exceptions.py
yggdrasil_shared/formatters.py
yggdrasil_shared/handlers.py
yggdrasil_shared/middlewares.py
yggdrasil_shared/models.py
yggdrasil_shared/permissions.py
yggdrasil_shared/responses.py
yggdrasil_shared/s3_client.py
yggdrasil_shared/schema.py
yggdrasil_shared/test_utils.py
yggdrasil_shared/utils.py
yggdrasil_shared/i18n/__init__.py
yggdrasil_shared/i18n/translate.py
yggdrasil_shared/monkey_patch/__init__.py
yggdrasil_shared/monkey_patch/werkzeug.py
yggdrasil_shared-0.0.28.dist-info/METADATA
yggdrasil_shared-0.0.28.dist-info/WHEEL
yggdrasil_shared-0.0.28.dist-info/top_level.txt
yggdrasil_shared-0.0.28.dist-info/zip-safe
yggdrasil_shared-0.0.28.dist-info/RECORD
